randomix.py
randomix-0.1.2.dist-info/LICENSE
randomix-0.1.2.dist-info/METADATA
randomix-0.1.2.dist-info/WHEEL
randomix-0.1.2.dist-info/top_level.txt
randomix-0.1.2.dist-info/RECORD
