Metadata-Version: 2.2
Name: randomix
Version: 0.1.2
Summary: A library for key management in JAX.
Author-email: "Tuomas J. Lukka" <tjl@hipcode.fi>
License:                                  Apache License
Project-URL: Homepage, https://github.com/tjltjl/randomix
Project-URL: Repository, https://github.com/tjltjl/randomix
Requires-Python: >=3.9
License-File: LICENSE
Requires-Dist: jax
Requires-Dist: jaxlib
Provides-Extra: dev
Requires-Dist: pytest; extra == "dev"
Requires-Dist: twine; extra == "dev"
